Metadata-Version: 2.1
Name: fcapy
Version: 0.1.4.5
Summary: A library to work with formal (and pattern) contexts, concepts, lattices
Author: Egor Dudyrev
License:                     GNU GENERAL PUBLIC LICENSE
Project-URL: Homepage, https://github.com/EgorDudyrev/FCApy
Keywords: python,fca,formal-concept-analysis
Classifier: Programming Language :: Python :: 3
Classifier: Programming Language :: Python :: 3.9
Classifier: License :: OSI Approved :: GNU General Public License v3 (GPLv3)
Classifier: Operating System :: OS Independent
Requires-Python: >=3.9
License-File: LICENSE
Requires-Dist: numpy>=1.20
Requires-Dist: scikit-mine>=1
Requires-Dist: bitarray>=3
Requires-Dist: tqdm
Requires-Dist: pandas
Requires-Dist: frozendict
Requires-Dist: pydantic
Requires-Dist: joblib
Requires-Dist: scikit-learn
Requires-Dist: matplotlib
Requires-Dist: networkx>=2.5
Requires-Dist: caspailleur>=0.2.1
Provides-Extra: docs
Requires-Dist: numpydoc; extra == "docs"
Requires-Dist: sphinx_rtd_theme; extra == "docs"
Requires-Dist: sphinx<8; extra == "docs"
Requires-Dist: nbsphinx; extra == "docs"
Requires-Dist: alabaster==0.7.16; extra == "docs"
Provides-Extra: ml
Requires-Dist: xgboost; extra == "ml"
Provides-Extra: visualizer
Requires-Dist: plotly; extra == "visualizer"
Provides-Extra: all
Requires-Dist: xgboost; extra == "all"
Requires-Dist: plotly; extra == "all"
Provides-Extra: tests
Requires-Dist: xgboost; extra == "tests"
Requires-Dist: plotly; extra == "tests"
Requires-Dist: numpydoc; extra == "tests"
Requires-Dist: sphinx_rtd_theme; extra == "tests"
Requires-Dist: sphinx<8; extra == "tests"
Requires-Dist: nbsphinx; extra == "tests"
Requires-Dist: alabaster==0.7.16; extra == "tests"
